DigLabTools-0.0.7.data/data/DigLabTools/README.md
DigLabTools-0.0.7.data/data/DigLabTools/VERSION
DigLabTools-0.0.7.data/data/DigLabTools/requirements.txt
diglab_utils/__init__.py
diglab_utils/conversion.py
diglab_utils/provenance.py
diglab_utils/test_conversion.py
diglab_utils/test_utils.py
elab_bridge/__init__.py
elab_bridge/cli.py
elab_bridge/project_building.py
elab_bridge/project_control.py
elab_bridge/project_validation.py
elab_bridge/server_interface.py
elab_bridge/template_parts/2photon.json
elab_bridge/template_parts/eyelink.json
elab_bridge/template_parts/general.json
elab_bridge/template_parts/kinarm.json
elab_bridge/template_parts/rodent_ephys.json
elab_bridge/tests/__init__.py
elab_bridge/tests/test_cli.py
elab_bridge/tests/test_project_building.py
elab_bridge/tests/test_project_control.py
elab_bridge/tests/test_project_validation.py
elab_bridge/tests/test_server_interface.py
redcap_bridge/__init__.py
redcap_bridge/cli.py
redcap_bridge/project_building.py
redcap_bridge/project_control.py
redcap_bridge/project_validation.py
redcap_bridge/server_interface.py
redcap_bridge/utils.py
redcap_bridge/template_parts/_provenance.csv
redcap_bridge/template_parts/array_sua_units.csv
redcap_bridge/template_parts/eyelink.csv
redcap_bridge/template_parts/general.csv
redcap_bridge/template_parts/kinarm.csv
redcap_bridge/template_parts/patch_general.csv
redcap_bridge/tests/__init__.py
redcap_bridge/tests/check_connectivity.py
redcap_bridge/tests/test_cli.py
redcap_bridge/tests/test_project_building.py
redcap_bridge/tests/test_project_control.py
redcap_bridge/tests/test_project_validation.py
redcap_bridge/tests/test_server_interface.py
redcap_bridge/tests/test_utils.py
DigLabTools-0.0.7.dist-info/LICENSE
DigLabTools-0.0.7.dist-info/METADATA
DigLabTools-0.0.7.dist-info/WHEEL
DigLabTools-0.0.7.dist-info/entry_points.txt
DigLabTools-0.0.7.dist-info/top_level.txt
DigLabTools-0.0.7.dist-info/RECORD
