Metadata-Version: 2.1
Name: DigLabTools
Version: 0.0.7
Summary: Tools to interact with the DigLab metadata collection standard
Author: Julia Sprenger, Jeremy Garcia, Killian Rochet
License: MIT
Requires-Python: >=3.8
License-File: LICENSE
Requires-Dist: pandas
Requires-Dist: pytest
Requires-Dist: gitpython
Requires-Dist: pycap >=2.0.0
Requires-Dist: elabapi-python
Provides-Extra: test
Requires-Dist: pytest ; extra == 'test'
